LICENSE.txt
README.md
pyproject.toml
setup.py
src/Warbler.egg-info/PKG-INFO
src/Warbler.egg-info/SOURCES.txt
src/Warbler.egg-info/dependency_links.txt
src/Warbler.egg-info/requires.txt
src/Warbler.egg-info/top_level.txt
src/warbler/__init__.py
src/warbler/__main__.py
src/warbler/annotation.py
src/warbler/document.py
src/warbler/layout.py
src/warbler/page.py
src/warbler/shapes.py
src/warbler/util.py
src/warbler/warblertypes.py